LICENSE
MANIFEST.in
README.rst
setup.py
stream/__init__.py
stream/compat.py
stream/connection.py
stream/exceptions.py
stream/serializer.py
stream/transport.py
stream/client/__init__.py
stream/client/auth.py
stream/client/properties.py
stream/client/stream_client.py
stream/client/utils.py
stream_python_sdk.egg-info/PKG-INFO
stream_python_sdk.egg-info/SOURCES.txt
stream_python_sdk.egg-info/dependency_links.txt
stream_python_sdk.egg-info/requires.txt
stream_python_sdk.egg-info/top_level.txt
test_stream/__init__.py
test_stream/test_stream_client.py