Metadata-Version: 1.1
Name: stream-python-sdk
Version: 0.2
Summary: Stream SDK
Home-page: https://github.com/NetEase-Cloudsearch/stream-python-sdk
Author: Stream Developer
Author-email: hzhuangzhenxi@corp.netease.com
License: MIT License
Platform: UNKNOWN
Classifier: Development Status :: 5 - Production/Stable
Classifier: License :: OSI Approved :: MIT License
Classifier: Intended Audience :: Developers
Classifier: Operating System :: OS Independent
Classifier: Programming Language :: Python
Classifier: Programming Language :: Python :: 2
Classifier: Programming Language :: Python :: 2.6
Classifier: Programming Language :: Python :: 2.7
